TypedUnit/__init__.py
TypedUnit/_version.py
TypedUnit/directories.py
TypedUnit/helper.py
TypedUnit/units.py
TypedUnit/utils.py
typedunit-0.0.8.dist-info/licenses/LICENSE
typedunit-0.0.8.dist-info/METADATA
typedunit-0.0.8.dist-info/WHEEL
typedunit-0.0.8.dist-info/top_level.txt
typedunit-0.0.8.dist-info/RECORD
